test_pypackage/__init__.py
test_pypackage/__main__.py
test_pypackage/cli.py
test_pypackage/core.py
test_pypackage-1.0.2.dist-info/LICENSE
test_pypackage-1.0.2.dist-info/METADATA
test_pypackage-1.0.2.dist-info/WHEEL
test_pypackage-1.0.2.dist-info/entry_points.txt
test_pypackage-1.0.2.dist-info/top_level.txt
test_pypackage-1.0.2.dist-info/RECORD
