Metadata-Version: 2.2
Name: test-pypackage
Version: 1.0.2
Summary: A test package for our pypackage cookiecutter.
Project-URL: Repository, https://github.com/hypothesis/test-pypackage
Project-URL: Issues, https://github.com/hypothesis/test-pypackage/issues
Project-URL: Changelog, https://github.com/hypothesis/test-pypackage/releases
Classifier: Programming Language :: Python :: 3
Classifier: License :: OSI Approved :: BSD License
Classifier: Intended Audience :: Developers
Requires-Python: >=3.8
License-File: LICENSE
Requires-Dist: sqlalchemy
Requires-Dist: psycopg2
